entest_cognito_userpool/__init__.py
entest_cognito_userpool/py.typed
entest_cognito_userpool/_jsii/__init__.py
entest_cognito_userpool/_jsii/entest-cdk-chatbot@0.0.2.jsii.tgz
entest_cognito_userpool-0.0.2.dist-info/LICENSE
entest_cognito_userpool-0.0.2.dist-info/METADATA
entest_cognito_userpool-0.0.2.dist-info/WHEEL
entest_cognito_userpool-0.0.2.dist-info/top_level.txt
entest_cognito_userpool-0.0.2.dist-info/RECORD
